[{"locale": "en", "description": "FANTASTIO COMICS\nPAGE 13\nSo, SAMSON... YOU'VE\nUTTERLY DESTROYED\nMY SECRET CITY.\nBUT I'LL GET YOU YET!\nTHAT SOUNDS.\nLIKE THE\nMASTER-MIND!\nTHAT GUN S USELESS TO YOU...\nNO SHELL CAN PIERCE\nTHIS FORTRESS/\nCAN, EH?,\n73HS ON'HO,\nHOW ABOUT THE\nWHOLE CANNON?\nI'M NOT CALUGHT YET--\nMY DEAR SAMSON!\nA PYRAMID,EH?\nULP\nCRASA\nJUST LIKE IN EGYPT, HUHP\nTHIS IS BETTER THAN A SHOOTING\nGALLERY! NOW WHAT SHALL I HIT?\nI WAS PREPARED\nFOR THIS; SAMSON!\nONE WHIFF AND\nYOU DIE!\nHOLD YOUR\nBREATH, DAVID!\nHIT THE DARK\nPATCH ON THE\nSIDE WALL!\nYES...HE..ER-FELL\nOFF THE MOUNTAIN\nTRAIL AS WE WERE\nBRINGING HIM\nBACK!\nROULF! SO YOU WERE\nBEHIND ALL THIS?\nYES..YOU VILLAIN!\nYOU HAVE SPOILED\nTHE BEAUTIFLUL\nPLANS OF MY\nFATHERLAND!\nGREAT WORK, SAMSON!\nTOO BAD THE LEADER\nWAS NOT BROUGHT\nTO TRIAL!\nGEE WHIZ....THE\nEDITOR OF THE\nSTANDARD!\nRAY FOR\nSAMSON!\nCLICA\nSOCK/\nREAD ABOUT SAMSON AND\nDAVID IN THE NEXT ISSUE\n13\nFANTASTIC COMICS IS ON SALE THE 10th OF EVERY MONTH\n", "bb": [{"x": 30, "y": 15}, {"x": 968, "y": 15}, {"x": 968, "y": 1369}, {"x": 30, "y": 1369}]}, {"locale": "", "description": "FANTASTIO", "bb": [{"x": 384, "y": 15}, {"x": 527, "y": 15}, {"x": 527, "y": 31}, {"x": 384, "y": 31}]}, {"locale": "", "description": "COMICS", "bb": [{"x": 540, "y": 15}, {"x": 643, "y": 15}, {"x": 643, "y": 31}, {"x": 540, "y": 31}]}, {"locale": "", "description": "PAGE", "bb": [{"x": 866, "y": 19}, {"x": 916, "y": 18}, {"x": 916, "y": 34}, {"x": 866, "y": 35}]}, {"locale": "", "description": "13", "bb": [{"x": 930, "y": 17}, {"x": 949, "y": 17}, {"x": 949, "y": 34}, {"x": 930, "y": 34}]}, {"locale": "", "description": "So,", "bb": [{"x": 54, "y": 51}, {"x": 84, "y": 51}, {"x": 84, "y": 68}, {"x": 54, "y": 68}]}, {"locale": "", "description": "SAMSON...", "bb": [{"x": 86, "y": 51}, {"x": 174, "y": 51}, {"x": 174, "y": 68}, {"x": 86, "y": 68}]}, {"locale": "", "description": "YOU'VE", "bb": [{"x": 176, "y": 52}, {"x": 239, "y": 52}, {"x": 239, "y": 65}, {"x": 176, "y": 65}]}, {"locale": "", "description": "UTTERLY", "bb": [{"x": 47, "y": 66}, {"x": 116, "y": 66}, {"x": 116, "y": 84}, {"x": 47, "y": 84}]}, {"locale": "", "description": "DESTROYED", "bb": [{"x": 128, "y": 66}, {"x": 233, "y": 66}, {"x": 233, "y": 84}, {"x": 128, "y": 84}]}, {"locale": "", "description": "MY", "bb": [{"x": 40, "y": 81}, {"x": 69, "y": 81}, {"x": 69, "y": 97}, {"x": 40, "y": 97}]}, {"locale": "", "description": "SECRET", "bb": [{"x": 80, "y": 81}, {"x": 147, "y": 81}, {"x": 147, "y": 98}, {"x": 80, "y": 98}]}, {"locale": "", "description": "CITY.", "bb": [{"x": 170, "y": 81}, {"x": 204, "y": 81}, {"x": 204, "y": 98}, {"x": 170, "y": 98}]}, {"locale": "", "description": "BUT", "bb": [{"x": 43, "y": 99}, {"x": 76, "y": 98}, {"x": 76, "y": 116}, {"x": 43, "y": 117}]}, {"locale": "", "description": "I'LL", "bb": [{"x": 78, "y": 98}, {"x": 108, "y": 97}, {"x": 108, "y": 115}, {"x": 78, "y": 116}]}, {"locale": "", "description": "GET", "bb": [{"x": 114, "y": 100}, {"x": 148, "y": 99}, {"x": 148, "y": 112}, {"x": 114, "y": 113}]}, {"locale": "", "description": "YOU", "bb": [{"x": 155, "y": 96}, {"x": 188, "y": 95}, {"x": 188, "y": 113}, {"x": 155, "y": 114}]}, {"locale": "", "description": "YET!", "bb": [{"x": 197, "y": 95}, {"x": 236, "y": 94}, {"x": 236, "y": 113}, {"x": 197, "y": 114}]}, {"locale": "", "description": "THAT", "bb": [{"x": 299, "y": 66}, {"x": 348, "y": 66}, {"x": 348, "y": 79}, {"x": 299, "y": 79}]}, {"locale": "", "description": "SOUNDS.", "bb": [{"x": 358, "y": 65}, {"x": 445, "y": 65}, {"x": 445, "y": 80}, {"x": 358, "y": 80}]}, {"locale": "", "description": "LIKE", "bb": [{"x": 312, "y": 84}, {"x": 354, "y": 84}, {"x": 354, "y": 96}, {"x": 312, "y": 96}]}, {"locale": "", "description": "THE", "bb": [{"x": 365, "y": 83}, {"x": 402, "y": 83}, {"x": 402, "y": 96}, {"x": 365, "y": 96}]}, {"locale": "", "description": "MASTER-MIND!", "bb": [{"x": 304, "y": 99}, {"x": 438, "y": 99}, {"x": 438, "y": 115}, {"x": 304, "y": 115}]}, {"locale": "", "description": "THAT", "bb": [{"x": 625, "y": 54}, {"x": 673, "y": 54}, {"x": 673, "y": 67}, {"x": 625, "y": 67}]}, {"locale": "", "description": "GUN", "bb": [{"x": 682, "y": 54}, {"x": 722, "y": 54}, {"x": 722, "y": 67}, {"x": 682, "y": 67}]}, {"locale": "", "description": "S", "bb": [{"x": 727, "y": 52}, {"x": 767, "y": 52}, {"x": 767, "y": 69}, {"x": 727, "y": 69}]}, {"locale": "", "description": "USELESS", "bb": [{"x": 769, "y": 51}, {"x": 842, "y": 51}, {"x": 842, "y": 68}, {"x": 769, "y": 68}]}, {"locale": "", "description": "TO", "bb": [{"x": 852, "y": 54}, {"x": 878, "y": 54}, {"x": 878, "y": 66}, {"x": 852, "y": 66}]}, {"locale": "", "description": "YOU...", "bb": [{"x": 887, "y": 53}, {"x": 949, "y": 53}, {"x": 949, "y": 67}, {"x": 887, "y": 67}]}, {"locale": "", "description": "NO", "bb": [{"x": 747, "y": 71}, {"x": 775, "y": 71}, {"x": 775, "y": 85}, {"x": 747, "y": 85}]}, {"locale": "", "description": "SHELL", "bb": [{"x": 788, "y": 68}, {"x": 848, "y": 68}, {"x": 848, "y": 84}, {"x": 788, "y": 84}]}, {"locale": "", "description": "CAN", "bb": [{"x": 855, "y": 70}, {"x": 889, "y": 70}, {"x": 889, "y": 83}, {"x": 855, "y": 83}]}, {"locale": "", "description": "PIERCE", "bb": [{"x": 899, "y": 67}, {"x": 968, "y": 67}, {"x": 968, "y": 85}, {"x": 899, "y": 85}]}, {"locale": "", "description": "THIS", "bb": [{"x": 796, "y": 89}, {"x": 842, "y": 89}, {"x": 842, "y": 103}, {"x": 796, "y": 103}]}, {"locale": "", "description": "FORTRESS/", "bb": [{"x": 852, "y": 85}, {"x": 957, "y": 85}, {"x": 957, "y": 103}, {"x": 852, "y": 103}]}, {"locale": "", "description": "CAN,", "bb": [{"x": 672, "y": 132}, {"x": 723, "y": 132}, {"x": 723, "y": 151}, {"x": 672, "y": 151}]}, {"locale": "", "description": "EH?,", "bb": [{"x": 725, "y": 132}, {"x": 767, "y": 132}, {"x": 767, "y": 152}, {"x": 725, "y": 152}]}, {"locale": "", "description": "73HS", "bb": [{"x": 806, "y": 132}, {"x": 735, "y": 131}, {"x": 735, "y": 111}, {"x": 806, "y": 112}]}, {"locale": "", "description": "ON'HO,", "bb": [{"x": 737, "y": 131}, {"x": 650, "y": 130}, {"x": 650, "y": 111}, {"x": 737, "y": 112}]}, {"locale": "", "description": "HOW", "bb": [{"x": 139, "y": 380}, {"x": 189, "y": 380}, {"x": 189, "y": 395}, {"x": 139, "y": 395}]}, {"locale": "", "description": "ABOUT", "bb": [{"x": 198, "y": 382}, {"x": 262, "y": 382}, {"x": 262, "y": 396}, {"x": 198, "y": 396}]}, {"locale": "", "description": "THE", "bb": [{"x": 269, "y": 382}, {"x": 305, "y": 382}, {"x": 305, "y": 395}, {"x": 269, "y": 395}]}, {"locale": "", "description": "WHOLE", "bb": [{"x": 143, "y": 400}, {"x": 213, "y": 400}, {"x": 213, "y": 413}, {"x": 143, "y": 413}]}, {"locale": "", "description": "CANNON?", "bb": [{"x": 223, "y": 400}, {"x": 315, "y": 400}, {"x": 315, "y": 413}, {"x": 223, "y": 413}]}, {"locale": "", "description": "I'M", "bb": [{"x": 526, "y": 380}, {"x": 555, "y": 380}, {"x": 555, "y": 397}, {"x": 526, "y": 397}]}, {"locale": "", "description": "NOT", "bb": [{"x": 563, "y": 382}, {"x": 597, "y": 382}, {"x": 597, "y": 397}, {"x": 563, "y": 397}]}, {"locale": "", "description": "CALUGHT", "bb": [{"x": 605, "y": 383}, {"x": 673, "y": 383}, {"x": 673, "y": 398}, {"x": 605, "y": 398}]}, {"locale": "", "description": "YET--", "bb": [{"x": 684, "y": 381}, {"x": 732, "y": 381}, {"x": 732, "y": 399}, {"x": 684, "y": 399}]}, {"locale": "", "description": "MY", "bb": [{"x": 510, "y": 402}, {"x": 541, "y": 402}, {"x": 541, "y": 420}, {"x": 510, "y": 420}]}, {"locale": "", "description": "DEAR", "bb": [{"x": 549, "y": 404}, {"x": 594, "y": 404}, {"x": 594, "y": 418}, {"x": 549, "y": 418}]}, {"locale": "", "description": "SAMSON!", "bb": [{"x": 599, "y": 402}, {"x": 681, "y": 402}, {"x": 681, "y": 420}, {"x": 599, "y": 420}]}, {"locale": "", "description": "A", "bb": [{"x": 810, "y": 389}, {"x": 828, "y": 389}, {"x": 828, "y": 407}, {"x": 810, "y": 407}]}, {"locale": "", "description": "PYRAMID,EH?", "bb": [{"x": 836, "y": 391}, {"x": 966, "y": 392}, {"x": 966, "y": 411}, {"x": 836, "y": 410}]}, {"locale": "", "description": "ULP", "bb": [{"x": 396, "y": 413}, {"x": 459, "y": 409}, {"x": 461, "y": 440}, {"x": 398, "y": 444}]}, {"locale": "", "description": "CRASA", "bb": [{"x": 309, "y": 543}, {"x": 381, "y": 517}, {"x": 387, "y": 535}, {"x": 315, "y": 561}]}, {"locale": "", "description": "JUST", "bb": [{"x": 518, "y": 534}, {"x": 570, "y": 534}, {"x": 570, "y": 555}, {"x": 518, "y": 555}]}, {"locale": "", "description": "LIKE", "bb": [{"x": 576, "y": 536}, {"x": 616, "y": 536}, {"x": 616, "y": 552}, {"x": 576, "y": 552}]}, {"locale": "", "description": "IN", "bb": [{"x": 623, "y": 538}, {"x": 637, "y": 538}, {"x": 637, "y": 551}, {"x": 623, "y": 551}]}, {"locale": "", "description": "EGYPT,", "bb": [{"x": 644, "y": 536}, {"x": 703, "y": 536}, {"x": 703, "y": 555}, {"x": 644, "y": 555}]}, {"locale": "", "description": "HUHP", "bb": [{"x": 708, "y": 535}, {"x": 757, "y": 535}, {"x": 757, "y": 556}, {"x": 708, "y": 556}]}, {"locale": "", "description": "THIS", "bb": [{"x": 155, "y": 704}, {"x": 199, "y": 704}, {"x": 199, "y": 721}, {"x": 155, "y": 721}]}, {"locale": "", "description": "IS", "bb": [{"x": 208, "y": 708}, {"x": 223, "y": 708}, {"x": 223, "y": 720}, {"x": 208, "y": 720}]}, {"locale": "", "description": "BETTER", "bb": [{"x": 235, "y": 707}, {"x": 308, "y": 707}, {"x": 308, "y": 721}, {"x": 235, "y": 721}]}, {"locale": "", "description": "THAN", "bb": [{"x": 315, "y": 707}, {"x": 364, "y": 707}, {"x": 364, "y": 721}, {"x": 315, "y": 721}]}, {"locale": "", "description": "A", "bb": [{"x": 368, "y": 706}, {"x": 380, "y": 706}, {"x": 380, "y": 720}, {"x": 368, "y": 720}]}, {"locale": "", "description": "SHOOTING", "bb": [{"x": 389, "y": 707}, {"x": 478, "y": 707}, {"x": 478, "y": 720}, {"x": 389, "y": 720}]}, {"locale": "", "description": "GALLERY!", "bb": [{"x": 155, "y": 725}, {"x": 248, "y": 725}, {"x": 248, "y": 741}, {"x": 155, "y": 741}]}, {"locale": "", "description": "NOW", "bb": [{"x": 256, "y": 723}, {"x": 313, "y": 723}, {"x": 313, "y": 741}, {"x": 256, "y": 741}]}, {"locale": "", "description": "WHAT", "bb": [{"x": 315, "y": 723}, {"x": 351, "y": 723}, {"x": 351, "y": 741}, {"x": 315, "y": 741}]}, {"locale": "", "description": "SHALL", "bb": [{"x": 355, "y": 725}, {"x": 412, "y": 725}, {"x": 412, "y": 740}, {"x": 355, "y": 740}]}, {"locale": "", "description": "I", "bb": [{"x": 420, "y": 723}, {"x": 434, "y": 723}, {"x": 434, "y": 741}, {"x": 420, "y": 741}]}, {"locale": "", "description": "HIT?", "bb": [{"x": 433, "y": 726}, {"x": 472, "y": 726}, {"x": 472, "y": 739}, {"x": 433, "y": 739}]}, {"locale": "", "description": "I", "bb": [{"x": 764, "y": 725}, {"x": 777, "y": 725}, {"x": 777, "y": 743}, {"x": 764, "y": 743}]}, {"locale": "", "description": "WAS", "bb": [{"x": 779, "y": 725}, {"x": 805, "y": 725}, {"x": 805, "y": 743}, {"x": 779, "y": 743}]}, {"locale": "", "description": "PREPARED", "bb": [{"x": 812, "y": 727}, {"x": 921, "y": 728}, {"x": 921, "y": 744}, {"x": 812, "y": 743}]}, {"locale": "", "description": "FOR", "bb": [{"x": 727, "y": 747}, {"x": 771, "y": 747}, {"x": 771, "y": 761}, {"x": 727, "y": 761}]}, {"locale": "", "description": "THIS;", "bb": [{"x": 778, "y": 748}, {"x": 826, "y": 748}, {"x": 826, "y": 763}, {"x": 778, "y": 763}]}, {"locale": "", "description": "SAMSON!", "bb": [{"x": 833, "y": 746}, {"x": 923, "y": 746}, {"x": 923, "y": 763}, {"x": 833, "y": 763}]}, {"locale": "", "description": "ONE", "bb": [{"x": 744, "y": 764}, {"x": 784, "y": 764}, {"x": 784, "y": 777}, {"x": 744, "y": 777}]}, {"locale": "", "description": "WHIFF", "bb": [{"x": 792, "y": 761}, {"x": 850, "y": 761}, {"x": 850, "y": 778}, {"x": 792, "y": 778}]}, {"locale": "", "description": "AND", "bb": [{"x": 856, "y": 761}, {"x": 896, "y": 761}, {"x": 896, "y": 778}, {"x": 856, "y": 778}]}, {"locale": "", "description": "YOU", "bb": [{"x": 795, "y": 777}, {"x": 833, "y": 778}, {"x": 833, "y": 794}, {"x": 795, "y": 793}]}, {"locale": "", "description": "DIE!", "bb": [{"x": 843, "y": 778}, {"x": 881, "y": 779}, {"x": 881, "y": 795}, {"x": 843, "y": 794}]}, {"locale": "", "description": "HOLD", "bb": [{"x": 536, "y": 732}, {"x": 585, "y": 732}, {"x": 585, "y": 746}, {"x": 536, "y": 746}]}, {"locale": "", "description": "YOUR", "bb": [{"x": 593, "y": 733}, {"x": 645, "y": 733}, {"x": 645, "y": 746}, {"x": 593, "y": 746}]}, {"locale": "", "description": "BREATH,", "bb": [{"x": 515, "y": 750}, {"x": 594, "y": 749}, {"x": 594, "y": 772}, {"x": 515, "y": 773}]}, {"locale": "", "description": "DAVID!", "bb": [{"x": 596, "y": 750}, {"x": 651, "y": 749}, {"x": 651, "y": 771}, {"x": 596, "y": 772}]}, {"locale": "", "description": "HIT", "bb": [{"x": 48, "y": 815}, {"x": 74, "y": 815}, {"x": 74, "y": 828}, {"x": 48, "y": 828}]}, {"locale": "", "description": "THE", "bb": [{"x": 80, "y": 814}, {"x": 114, "y": 813}, {"x": 114, "y": 828}, {"x": 80, "y": 829}]}, {"locale": "", "description": "DARK", "bb": [{"x": 123, "y": 813}, {"x": 174, "y": 812}, {"x": 174, "y": 828}, {"x": 123, "y": 829}]}, {"locale": "", "description": "PATCH", "bb": [{"x": 41, "y": 835}, {"x": 91, "y": 835}, {"x": 91, "y": 848}, {"x": 41, "y": 848}]}, {"locale": "", "description": "ON", "bb": [{"x": 97, "y": 836}, {"x": 120, "y": 836}, {"x": 120, "y": 848}, {"x": 97, "y": 848}]}, {"locale": "", "description": "THE", "bb": [{"x": 129, "y": 835}, {"x": 163, "y": 835}, {"x": 163, "y": 848}, {"x": 129, "y": 848}]}, {"locale": "", "description": "SIDE", "bb": [{"x": 47, "y": 855}, {"x": 83, "y": 855}, {"x": 83, "y": 869}, {"x": 47, "y": 869}]}, {"locale": "", "description": "WALL!", "bb": [{"x": 92, "y": 854}, {"x": 149, "y": 854}, {"x": 149, "y": 870}, {"x": 92, "y": 870}]}, {"locale": "", "description": "YES...HE..ER-FELL", "bb": [{"x": 798, "y": 1031}, {"x": 964, "y": 1031}, {"x": 964, "y": 1050}, {"x": 798, "y": 1050}]}, {"locale": "", "description": "OFF", "bb": [{"x": 790, "y": 1055}, {"x": 824, "y": 1055}, {"x": 824, "y": 1066}, {"x": 790, "y": 1066}]}, {"locale": "", "description": "THE", "bb": [{"x": 830, "y": 1054}, {"x": 861, "y": 1054}, {"x": 861, "y": 1068}, {"x": 830, "y": 1068}]}, {"locale": "", "description": "MOUNTAIN", "bb": [{"x": 865, "y": 1054}, {"x": 955, "y": 1054}, {"x": 955, "y": 1069}, {"x": 865, "y": 1069}]}, {"locale": "", "description": "TRAIL", "bb": [{"x": 782, "y": 1067}, {"x": 838, "y": 1067}, {"x": 838, "y": 1086}, {"x": 782, "y": 1086}]}, {"locale": "", "description": "AS", "bb": [{"x": 847, "y": 1067}, {"x": 866, "y": 1067}, {"x": 866, "y": 1086}, {"x": 847, "y": 1086}]}, {"locale": "", "description": "WE", "bb": [{"x": 871, "y": 1067}, {"x": 898, "y": 1067}, {"x": 898, "y": 1084}, {"x": 871, "y": 1084}]}, {"locale": "", "description": "WERE", "bb": [{"x": 907, "y": 1067}, {"x": 962, "y": 1067}, {"x": 962, "y": 1085}, {"x": 907, "y": 1085}]}, {"locale": "", "description": "BRINGING", "bb": [{"x": 808, "y": 1086}, {"x": 897, "y": 1087}, {"x": 897, "y": 1103}, {"x": 808, "y": 1102}]}, {"locale": "", "description": "HIM", "bb": [{"x": 904, "y": 1087}, {"x": 940, "y": 1087}, {"x": 940, "y": 1103}, {"x": 904, "y": 1103}]}, {"locale": "", "description": "BACK!", "bb": [{"x": 873, "y": 1103}, {"x": 936, "y": 1103}, {"x": 936, "y": 1121}, {"x": 873, "y": 1121}]}, {"locale": "", "description": "ROULF!", "bb": [{"x": 160, "y": 1032}, {"x": 246, "y": 1032}, {"x": 246, "y": 1049}, {"x": 160, "y": 1049}]}, {"locale": "", "description": "SO", "bb": [{"x": 254, "y": 1035}, {"x": 279, "y": 1035}, {"x": 279, "y": 1049}, {"x": 254, "y": 1049}]}, {"locale": "", "description": "YOU", "bb": [{"x": 290, "y": 1034}, {"x": 330, "y": 1034}, {"x": 330, "y": 1048}, {"x": 290, "y": 1048}]}, {"locale": "", "description": "WERE", "bb": [{"x": 340, "y": 1035}, {"x": 397, "y": 1035}, {"x": 397, "y": 1049}, {"x": 340, "y": 1049}]}, {"locale": "", "description": "BEHIND", "bb": [{"x": 246, "y": 1055}, {"x": 317, "y": 1055}, {"x": 317, "y": 1068}, {"x": 246, "y": 1068}]}, {"locale": "", "description": "ALL", "bb": [{"x": 326, "y": 1054}, {"x": 359, "y": 1054}, {"x": 359, "y": 1068}, {"x": 326, "y": 1068}]}, {"locale": "", "description": "THIS?", "bb": [{"x": 365, "y": 1055}, {"x": 422, "y": 1055}, {"x": 422, "y": 1069}, {"x": 365, "y": 1069}]}, {"locale": "", "description": "YES..YOU", "bb": [{"x": 32, "y": 1062}, {"x": 117, "y": 1062}, {"x": 117, "y": 1082}, {"x": 32, "y": 1082}]}, {"locale": "", "description": "VILLAIN!", "bb": [{"x": 124, "y": 1064}, {"x": 199, "y": 1064}, {"x": 199, "y": 1080}, {"x": 124, "y": 1080}]}, {"locale": "", "description": "YOU", "bb": [{"x": 30, "y": 1083}, {"x": 66, "y": 1083}, {"x": 66, "y": 1101}, {"x": 30, "y": 1101}]}, {"locale": "", "description": "HAVE", "bb": [{"x": 76, "y": 1085}, {"x": 119, "y": 1085}, {"x": 119, "y": 1099}, {"x": 76, "y": 1099}]}, {"locale": "", "description": "SPOILED", "bb": [{"x": 128, "y": 1086}, {"x": 204, "y": 1086}, {"x": 204, "y": 1101}, {"x": 128, "y": 1101}]}, {"locale": "", "description": "THE", "bb": [{"x": 37, "y": 1102}, {"x": 67, "y": 1102}, {"x": 67, "y": 1116}, {"x": 37, "y": 1116}]}, {"locale": "", "description": "BEAUTIFLUL", "bb": [{"x": 76, "y": 1099}, {"x": 171, "y": 1099}, {"x": 171, "y": 1117}, {"x": 76, "y": 1117}]}, {"locale": "", "description": "PLANS", "bb": [{"x": 42, "y": 1117}, {"x": 97, "y": 1116}, {"x": 97, "y": 1135}, {"x": 42, "y": 1136}]}, {"locale": "", "description": "OF", "bb": [{"x": 104, "y": 1117}, {"x": 127, "y": 1117}, {"x": 127, "y": 1133}, {"x": 104, "y": 1133}]}, {"locale": "", "description": "MY", "bb": [{"x": 136, "y": 1116}, {"x": 165, "y": 1116}, {"x": 165, "y": 1134}, {"x": 136, "y": 1134}]}, {"locale": "", "description": "FATHERLAND!", "bb": [{"x": 39, "y": 1135}, {"x": 159, "y": 1135}, {"x": 159, "y": 1152}, {"x": 39, "y": 1152}]}, {"locale": "", "description": "GREAT", "bb": [{"x": 508, "y": 1034}, {"x": 578, "y": 1034}, {"x": 578, "y": 1053}, {"x": 508, "y": 1053}]}, {"locale": "", "description": "WORK,", "bb": [{"x": 587, "y": 1036}, {"x": 646, "y": 1036}, {"x": 646, "y": 1053}, {"x": 587, "y": 1053}]}, {"locale": "", "description": "SAMSON!", "bb": [{"x": 650, "y": 1037}, {"x": 737, "y": 1037}, {"x": 737, "y": 1054}, {"x": 650, "y": 1054}]}, {"locale": "", "description": "TOO", "bb": [{"x": 507, "y": 1056}, {"x": 551, "y": 1056}, {"x": 551, "y": 1074}, {"x": 507, "y": 1074}]}, {"locale": "", "description": "BAD", "bb": [{"x": 560, "y": 1059}, {"x": 596, "y": 1059}, {"x": 596, "y": 1074}, {"x": 560, "y": 1074}]}, {"locale": "", "description": "THE", "bb": [{"x": 604, "y": 1059}, {"x": 636, "y": 1059}, {"x": 636, "y": 1072}, {"x": 604, "y": 1072}]}, {"locale": "", "description": "LEADER", "bb": [{"x": 646, "y": 1056}, {"x": 710, "y": 1056}, {"x": 710, "y": 1074}, {"x": 646, "y": 1074}]}, {"locale": "", "description": "WAS", "bb": [{"x": 521, "y": 1080}, {"x": 560, "y": 1080}, {"x": 560, "y": 1093}, {"x": 521, "y": 1093}]}, {"locale": "", "description": "NOT", "bb": [{"x": 568, "y": 1080}, {"x": 605, "y": 1080}, {"x": 605, "y": 1093}, {"x": 568, "y": 1093}]}, {"locale": "", "description": "BROUGHT", "bb": [{"x": 617, "y": 1077}, {"x": 700, "y": 1077}, {"x": 700, "y": 1095}, {"x": 617, "y": 1095}]}, {"locale": "", "description": "TO", "bb": [{"x": 543, "y": 1099}, {"x": 568, "y": 1099}, {"x": 568, "y": 1110}, {"x": 543, "y": 1110}]}, {"locale": "", "description": "TRIAL!", "bb": [{"x": 575, "y": 1097}, {"x": 637, "y": 1097}, {"x": 637, "y": 1112}, {"x": 575, "y": 1112}]}, {"locale": "", "description": "GEE", "bb": [{"x": 322, "y": 1103}, {"x": 363, "y": 1103}, {"x": 363, "y": 1120}, {"x": 322, "y": 1120}]}, {"locale": "", "description": "WHIZ....THE", "bb": [{"x": 371, "y": 1105}, {"x": 481, "y": 1106}, {"x": 481, "y": 1122}, {"x": 371, "y": 1121}]}, {"locale": "", "description": "EDITOR", "bb": [{"x": 332, "y": 1127}, {"x": 402, "y": 1127}, {"x": 402, "y": 1141}, {"x": 332, "y": 1141}]}, {"locale": "", "description": "OF", "bb": [{"x": 410, "y": 1127}, {"x": 435, "y": 1127}, {"x": 435, "y": 1140}, {"x": 410, "y": 1140}]}, {"locale": "", "description": "THE", "bb": [{"x": 440, "y": 1127}, {"x": 477, "y": 1127}, {"x": 477, "y": 1142}, {"x": 440, "y": 1142}]}, {"locale": "", "description": "STANDARD!", "bb": [{"x": 350, "y": 1146}, {"x": 463, "y": 1147}, {"x": 463, "y": 1163}, {"x": 350, "y": 1162}]}, {"locale": "", "description": "RAY", "bb": [{"x": 527, "y": 1166}, {"x": 579, "y": 1167}, {"x": 579, "y": 1183}, {"x": 527, "y": 1182}]}, {"locale": "", "description": "FOR", "bb": [{"x": 586, "y": 1168}, {"x": 626, "y": 1168}, {"x": 626, "y": 1186}, {"x": 586, "y": 1186}]}, {"locale": "", "description": "SAMSON!", "bb": [{"x": 530, "y": 1186}, {"x": 625, "y": 1185}, {"x": 625, "y": 1202}, {"x": 530, "y": 1203}]}, {"locale": "", "description": "CLICA", "bb": [{"x": 845, "y": 1174}, {"x": 889, "y": 1178}, {"x": 887, "y": 1192}, {"x": 844, "y": 1188}]}, {"locale": "", "description": "SOCK/", "bb": [{"x": 191, "y": 1232}, {"x": 259, "y": 1273}, {"x": 249, "y": 1289}, {"x": 181, "y": 1248}]}, {"locale": "", "description": "READ", "bb": [{"x": 521, "y": 1286}, {"x": 590, "y": 1286}, {"x": 590, "y": 1306}, {"x": 521, "y": 1306}]}, {"locale": "", "description": "ABOUT", "bb": [{"x": 600, "y": 1286}, {"x": 689, "y": 1286}, {"x": 689, "y": 1306}, {"x": 600, "y": 1306}]}, {"locale": "", "description": "SAMSON", "bb": [{"x": 699, "y": 1286}, {"x": 822, "y": 1286}, {"x": 822, "y": 1306}, {"x": 699, "y": 1306}]}, {"locale": "", "description": "AND", "bb": [{"x": 826, "y": 1286}, {"x": 888, "y": 1286}, {"x": 888, "y": 1306}, {"x": 826, "y": 1306}]}, {"locale": "", "description": "DAVID", "bb": [{"x": 544, "y": 1306}, {"x": 615, "y": 1306}, {"x": 615, "y": 1325}, {"x": 544, "y": 1325}]}, {"locale": "", "description": "IN", "bb": [{"x": 634, "y": 1307}, {"x": 655, "y": 1307}, {"x": 655, "y": 1326}, {"x": 634, "y": 1326}]}, {"locale": "", "description": "THE", "bb": [{"x": 684, "y": 1307}, {"x": 719, "y": 1307}, {"x": 719, "y": 1326}, {"x": 684, "y": 1326}]}, {"locale": "", "description": "NEXT", "bb": [{"x": 730, "y": 1307}, {"x": 795, "y": 1307}, {"x": 795, "y": 1326}, {"x": 730, "y": 1326}]}, {"locale": "", "description": "ISSUE", "bb": [{"x": 812, "y": 1308}, {"x": 881, "y": 1308}, {"x": 881, "y": 1327}, {"x": 812, "y": 1327}]}, {"locale": "", "description": "13", "bb": [{"x": 939, "y": 1304}, {"x": 961, "y": 1304}, {"x": 961, "y": 1325}, {"x": 939, "y": 1325}]}, {"locale": "", "description": "FANTASTIC", "bb": [{"x": 132, "y": 1346}, {"x": 300, "y": 1347}, {"x": 300, "y": 1369}, {"x": 132, "y": 1368}]}, {"locale": "", "description": "COMICS", "bb": [{"x": 303, "y": 1347}, {"x": 388, "y": 1347}, {"x": 388, "y": 1368}, {"x": 303, "y": 1368}]}, {"locale": "", "description": "IS", "bb": [{"x": 409, "y": 1347}, {"x": 451, "y": 1347}, {"x": 451, "y": 1368}, {"x": 409, "y": 1368}]}, {"locale": "", "description": "ON", "bb": [{"x": 457, "y": 1348}, {"x": 473, "y": 1348}, {"x": 473, "y": 1369}, {"x": 457, "y": 1369}]}, {"locale": "", "description": "SALE", "bb": [{"x": 484, "y": 1351}, {"x": 549, "y": 1351}, {"x": 549, "y": 1367}, {"x": 484, "y": 1367}]}, {"locale": "", "description": "THE", "bb": [{"x": 561, "y": 1351}, {"x": 609, "y": 1351}, {"x": 609, "y": 1366}, {"x": 561, "y": 1366}]}, {"locale": "", "description": "10th", "bb": [{"x": 621, "y": 1350}, {"x": 666, "y": 1350}, {"x": 666, "y": 1366}, {"x": 621, "y": 1366}]}, {"locale": "", "description": "OF", "bb": [{"x": 679, "y": 1351}, {"x": 710, "y": 1351}, {"x": 710, "y": 1367}, {"x": 679, "y": 1367}]}, {"locale": "", "description": "EVERY", "bb": [{"x": 724, "y": 1351}, {"x": 805, "y": 1351}, {"x": 805, "y": 1367}, {"x": 724, "y": 1367}]}, {"locale": "", "description": "MONTH", "bb": [{"x": 819, "y": 1350}, {"x": 910, "y": 1350}, {"x": 910, "y": 1367}, {"x": 819, "y": 1367}]}]